Library/JFROGDownloader.py
Library/__init__.py
jfrog_downloader-1.0.3.dist-info/licenses/LICENSE
jfrog_downloader-1.0.3.dist-info/METADATA
jfrog_downloader-1.0.3.dist-info/WHEEL
jfrog_downloader-1.0.3.dist-info/top_level.txt
jfrog_downloader-1.0.3.dist-info/RECORD
